Ldap3Library/__init__.py
Ldap3Library/connection_manager.py
Ldap3Library/query.py
Ldap3Library/version.py
robotframework_ldap3-0.1.0.dist-info/LICENSE
robotframework_ldap3-0.1.0.dist-info/METADATA
robotframework_ldap3-0.1.0.dist-info/WHEEL
robotframework_ldap3-0.1.0.dist-info/RECORD
